scoutbook_parser/__init__.py
scoutbook_parser/__main__.py
scoutbook_parser/advancement.py
scoutbook_parser/cli.py
scoutbook_parser/config.py
scoutbook_parser/config.toml
scoutbook_parser/parser.py
scoutbook_parser/personal_data.py
scoutbook_parser/requirements.toml
scoutbook_parser/utils.py
scoutbook_parser-0.17.0.dist-info/METADATA
scoutbook_parser-0.17.0.dist-info/WHEEL
scoutbook_parser-0.17.0.dist-info/entry_points.txt
scoutbook_parser-0.17.0.dist-info/RECORD
